supply_chains/__init__.py
supply_chains-0.1.0.dist-info/METADATA
supply_chains-0.1.0.dist-info/WHEEL
supply_chains-0.1.0.dist-info/entry_points.txt
supply_chains-0.1.0.dist-info/RECORD
