Metadata-Version: 2.4
Name: supply-chains
Version: 0.1.0
Summary: Add your description here
Author-email: Thomas Pinder <tompinder@live.co.uk>
Requires-Python: >=3.12
Requires-Dist: jax>=0.5.3
Requires-Dist: jaxlib>=0.5.3
Requires-Dist: numpyro>=0.18.0
Requires-Dist: optax>=0.2.4
